plonemeeting.restapi-2.10-py3.12-nspkg.pth
plonemeeting/restapi/__init__.py
plonemeeting/restapi/config.py
plonemeeting/restapi/configure.zcml
plonemeeting/restapi/interfaces.py
plonemeeting/restapi/overrides.zcml
plonemeeting/restapi/setuphandlers.py
plonemeeting/restapi/testing.py
plonemeeting/restapi/testing.zcml
plonemeeting/restapi/utils.py
plonemeeting/restapi/deserializer/__init__.py
plonemeeting/restapi/deserializer/atcontent.py
plonemeeting/restapi/deserializer/atfields.py
plonemeeting/restapi/deserializer/configure.zcml
plonemeeting/restapi/deserializer/dxfields.py
plonemeeting/restapi/locales/imio.history.pot
plonemeeting/restapi/locales/plone.pot
plonemeeting/restapi/locales/sync_pos.sh
plonemeeting/restapi/locales/en/LC_MESSAGES/imio.history.po
plonemeeting/restapi/locales/en/LC_MESSAGES/plone.po
plonemeeting/restapi/locales/fr/LC_MESSAGES/imio.history.po
plonemeeting/restapi/locales/fr/LC_MESSAGES/plone.po
plonemeeting/restapi/profiles/default/browserlayer.xml
plonemeeting/restapi/profiles/default/catalog.xml
plonemeeting/restapi/profiles/default/metadata.xml
plonemeeting/restapi/profiles/default/rolemap.xml
plonemeeting/restapi/profiles/testing/metadata.xml
plonemeeting/restapi/serializer/__init__.py
plonemeeting/restapi/serializer/annex.py
plonemeeting/restapi/serializer/atfields.py
plonemeeting/restapi/serializer/base.py
plonemeeting/restapi/serializer/catalog.py
plonemeeting/restapi/serializer/configure.zcml
plonemeeting/restapi/serializer/converters.py
plonemeeting/restapi/serializer/dxfields.py
plonemeeting/restapi/serializer/held_position.py
plonemeeting/restapi/serializer/item.py
plonemeeting/restapi/serializer/meeting.py
plonemeeting/restapi/serializer/meetingconfig.py
plonemeeting/restapi/serializer/pod_template.py
plonemeeting/restapi/serializer/summary.py
plonemeeting/restapi/serializer/user.py
plonemeeting/restapi/services/__init__.py
plonemeeting/restapi/services/add.py
plonemeeting/restapi/services/annex.py
plonemeeting_restapi-2.10.dist-info/licenses/LICENSE.GPL
plonemeeting_restapi-2.10.dist-info/licenses/LICENSE.rst
plonemeeting_restapi-2.10.dist-info/METADATA
plonemeeting_restapi-2.10.dist-info/WHEEL
plonemeeting_restapi-2.10.dist-info/entry_points.txt
plonemeeting_restapi-2.10.dist-info/namespace_packages.txt
plonemeeting_restapi-2.10.dist-info/top_level.txt
plonemeeting_restapi-2.10.dist-info/RECORD
