Metadata-Version: 2.4
Name: plonemeeting.restapi
Version: 2.10
Summary: Extended rest api service for Products.PloneMeeting usecases
Home-page: https://pypi.python.org/pypi/plonemeeting.restapi
Author: Gauthier Bastien
Author-email: gauthier@imio.be
License: GPL version 2
Keywords: Python Plone
Classifier: Development Status :: 4 - Beta
Classifier: Environment :: Web Environment
Classifier: Framework :: Plone
Classifier: Framework :: Plone :: 4.3
Classifier: Programming Language :: Python
Classifier: Programming Language :: Python :: 2.7
Classifier: Operating System :: OS Independent
Classifier: License :: OSI Approved :: GNU General Public License v2 (GPLv2)
License-File: LICENSE.GPL
License-File: LICENSE.rst
Requires-Dist: setuptools
Requires-Dist: Products.PloneMeeting
Requires-Dist: imio.restapi>=1.0a12
Requires-Dist: plone.restapi>=7.8.0
Provides-Extra: test
Requires-Dist: plone.restapi[test]; extra == "test"
Requires-Dist: Products.PloneMeeting[test]; extra == "test"
Dynamic: author
Dynamic: author-email
Dynamic: classifier
Dynamic: description
Dynamic: home-page
Dynamic: keywords
Dynamic: license
Dynamic: license-file
Dynamic: provides-extra
Dynamic: requires-dist
Dynamic: summary
